hoft/__init__.py
hoft/__version__.py
hoft/core/__init__.py
hoft/core/decorators.py
hoft/core/parsers_in.py
hoft/core/parsers_sig.py
hoft/core/sigs.py
hoft/core/utils.py
hoft-0.4.1.dist-info/DESCRIPTION.rst
hoft-0.4.1.dist-info/METADATA
hoft-0.4.1.dist-info/RECORD
hoft-0.4.1.dist-info/WHEEL
hoft-0.4.1.dist-info/metadata.json
hoft-0.4.1.dist-info/top_level.txt
