Metadata-Version: 2.0
Name: hoft
Version: 0.4.1
Summary: Higher Order Func Tools for Python2.7.
Home-page: https://github.com/sys-git/hoft
Author: Francis Horsman
Author-email: francis.horsman@gmail.com
License: MIT
Platform: UNKNOWN
Classifier: Development Status :: 4 - Beta
Classifier: Intended Audience :: Developers
Classifier: Operating System :: OS Independent
Classifier: Programming Language :: Python
Classifier: Programming Language :: Python :: 2.7
Classifier: Programming Language :: Python :: Implementation :: CPython
Classifier: Topic :: Software Development :: Libraries :: Python Modules
Requires: six
Requires: pip
Requires: enum34
